fastapi_cls/__init__.py
fastapi_cls/router.py
fastapi_cls/view_maker.py
fastapi_cls-0.1.3.dist-info/LICENSE
fastapi_cls-0.1.3.dist-info/METADATA
fastapi_cls-0.1.3.dist-info/WHEEL
fastapi_cls-0.1.3.dist-info/top_level.txt
fastapi_cls-0.1.3.dist-info/RECORD
