Metadata-Version: 2.1
Name: fastapi-cls
Version: 0.1.3
Summary: FastAPI framework class view router
Home-page: https://github.com/Carlos-Zen/fastapi_cls
Author: yfengli
Author-email: lizhichao@lilith.com
License: UNKNOWN
Platform: UNKNOWN
Classifier: Programming Language :: Python :: 3
Classifier: License :: OSI Approved :: MIT License
Classifier: Operating System :: OS Independent
License-File: LICENSE
